LICENSE.txt
MANIFEST.in
README.md
setup.cfg
setup.py
ojitos369/__init__.py
ojitos369/errors.py
ojitos369/text_format.py
ojitos369/try_it.py
ojitos369/types.py
ojitos369/utils.py
ojitos369.egg-info/PKG-INFO
ojitos369.egg-info/SOURCES.txt
ojitos369.egg-info/dependency_links.txt
ojitos369.egg-info/top_level.txt