Metadata-Version: 2.1
Name: ojitos369
Version: 1.0
Summary: Funciones de utilidades de ojitos369
Home-page: https://github.com/Ojitos369/ojitos369-pip
Author: Ojitos369
Author-email: ojitos369@gmail.com
License: LGPL v3
Keywords: Utilidades de ojitos369
License-File: LICENSE.txt
